README.rst
setup.py
littlebird/__init__.py
littlebird/__main__.py
littlebird/client.py
littlebird/urls.py
littlebird/web.py
littlebird.egg-info/PKG-INFO
littlebird.egg-info/SOURCES.txt
littlebird.egg-info/dependency_links.txt
littlebird.egg-info/requires.txt
littlebird.egg-info/top_level.txt