Metadata-Version: 1.1
Name: littlebird
Version: 0.0.0a1
Summary: Asyncronous twitter client library
Home-page: https://github.com/mrasband/littlebird
Author: Matt Rasband
Author-email: matt.rasband@gmail.com
License: MIT
Platform: UNKNOWN
Classifier: Development Status :: 3 - Alpha
Classifier: Intended Audience :: Developers
Classifier: License :: OSI Approved :: MIT License
Classifier: Operating System :: OS Independent
Classifier: Programming Language :: Python
Classifier: Programming Language :: Python :: 3.6
